arcscript/__init__.py
arcscript/cli.py
arcscript/transpiler.py
arcscript-0.1.3a0.dist-info/licenses/LICENSE
arcscript-0.1.3a0.dist-info/METADATA
arcscript-0.1.3a0.dist-info/WHEEL
arcscript-0.1.3a0.dist-info/entry_points.txt
arcscript-0.1.3a0.dist-info/top_level.txt
arcscript-0.1.3a0.dist-info/RECORD
