Metadata-Version: 2.4
Name: arcscript
Version: 0.1.3a0
Summary: A simple language that transpiles to JavaScript for easier web development.
Author-email: Aditya Tiwari <contact.aditya108@gmail.com>
License: GPL-3.0-or-later
Project-URL: Homepage, https://github.com/aditya-tiwari108/ArcScript
Project-URL: Bug Tracker, https://github.com/aditya-tiwari108/ArcScript/issues
Classifier: Development Status :: 3 - Alpha
Classifier: Programming Language :: Python :: 3
Classifier: License :: OSI Approved :: GNU General Public License v3 or later (GPLv3+)
Classifier: Operating System :: OS Independent
Classifier: Topic :: Software Development :: Compilers
Requires-Python: >=3.7
License-File: LICENSE
Requires-Dist: lark
Dynamic: license-file
